frutsel/__init__.py
frutsel/__main__.py
frutsel/vendor/__init__.py
frutsel/vendor/jsonpickle/__init__.py
frutsel/vendor/jsonpickle/backend.py
frutsel/vendor/jsonpickle/compat.py
frutsel/vendor/jsonpickle/errors.py
frutsel/vendor/jsonpickle/ext/__init__.py
frutsel/vendor/jsonpickle/ext/gmpy.py
frutsel/vendor/jsonpickle/ext/numpy.py
frutsel/vendor/jsonpickle/ext/pandas.py
frutsel/vendor/jsonpickle/ext/yaml.py
frutsel/vendor/jsonpickle/handlers.py
frutsel/vendor/jsonpickle/pickler.py
frutsel/vendor/jsonpickle/tags.py
frutsel/vendor/jsonpickle/tags_pd.py
frutsel/vendor/jsonpickle/unpickler.py
frutsel/vendor/jsonpickle/util.py
frutsel/vendor/jsonpickle/version.py
frutsel-0.17.16.dist-info/METADATA
frutsel-0.17.16.dist-info/WHEEL
frutsel-0.17.16.dist-info/entry_points.txt
frutsel-0.17.16.dist-info/RECORD
