Metadata-Version: 2.4
Name: frutsel
Version: 0.17.16
Summary: A copy-pastable, human readable, scalable database with an easy API.
License: LGPL-3.0-or-later
Author: maveobi
Author-email: path-fanfare-canon@duck.com
Requires-Python: >=3.8
Classifier: License :: OSI Approved :: GNU Lesser General Public License v3 or later (LGPLv3+)
Classifier: Programming Language :: Python :: 3
Classifier: Programming Language :: Python :: 3.8
Classifier: Programming Language :: Python :: 3.9
Classifier: Programming Language :: Python :: 3.10
Classifier: Programming Language :: Python :: 3.11
Classifier: Programming Language :: Python :: 3.12
Classifier: Programming Language :: Python :: 3.13
Classifier: Programming Language :: Python :: 3.14
